textual_keys/__init__.py
textual_keys/__main__.py
textual_keys/app.py
textual_keys/py.typed
textual_keys-1.3.0.dist-info/LICENSE
textual_keys-1.3.0.dist-info/METADATA
textual_keys-1.3.0.dist-info/WHEEL
textual_keys-1.3.0.dist-info/entry_points.txt
textual_keys-1.3.0.dist-info/top_level.txt
textual_keys-1.3.0.dist-info/RECORD
